rstcheck_core/__init__.py
rstcheck_core/__version__.py
rstcheck_core/_docutils.py
rstcheck_core/_extras.py
rstcheck_core/_sphinx.py
rstcheck_core/checker.py
rstcheck_core/config.py
rstcheck_core/inline_config.py
rstcheck_core/py.typed
rstcheck_core/runner.py
rstcheck_core/types.py
rstcheck_core-1.2.0.dist-info/AUTHORS.rst
rstcheck_core-1.2.0.dist-info/LICENSE
rstcheck_core-1.2.0.dist-info/METADATA
rstcheck_core-1.2.0.dist-info/WHEEL
rstcheck_core-1.2.0.dist-info/top_level.txt
rstcheck_core-1.2.0.dist-info/RECORD
